{"stat.useItem.minecraft.anvil":2,"stat.flyOneCm":4852,"stat.drop.minecraft.enchanting_table":1,"stat.walkOneCm":4216,"stat.drop":2,"stat.jump":19,"stat.playOneMinute":1273,"stat.pickup.minecraft.enchanting_table":2,"stat.leaveGame":1,"stat.useItem.minecraft.enchanting_table":2,"stat.pickup.minecraft.anvil":2,"stat.mineBlock.minecraft.anvil":2,"stat.mineBlock.minecraft.enchanting_table":2,"stat.useItem.minecraft.diamond_pickaxe":4,"stat.drop.minecraft.anvil":1,"stat.timeSinceDeath":1273,"stat.sprintOneCm":2373}